zebrazoom/GUIAllPy.py
zebrazoom/__init__.py
zebrazoom/__main__.py
zebrazoom/_subcommands.py
zebrazoom/clusteringAnalysis.py
zebrazoom/clusteringAnalysisPerFrame.py
zebrazoom/extractZZParametersFromTailAngle.py
zebrazoom/getTailExtremityFirstFrame.py
zebrazoom/kinematicParametersAnalysis.py
zebrazoom/kinematicParametersAnalysisCenterOfMassOnlyNoBoutsDetection.py
zebrazoom/recreateSuperStruct.py
zebrazoom/version.txt
zebrazoom/zebraZoomVideoAnalysis.py
zebrazoom/ZZoutput/example1/configUsed.json
zebrazoom/ZZoutput/example1/example1.avi
zebrazoom/ZZoutput/example1/intermediaryWellPosition.txt
zebrazoom/ZZoutput/example1/results_example1.txt
zebrazoom/ZZoutput/example2/configUsed.json
zebrazoom/ZZoutput/example2/example2.avi
zebrazoom/ZZoutput/example2/intermediaryWellPosition.txt
zebrazoom/ZZoutput/example2/results_example2.txt
zebrazoom/ZZoutput/example3/configUsed.json
zebrazoom/ZZoutput/example3/example3.avi
zebrazoom/ZZoutput/example3/intermediaryWellPosition.txt
zebrazoom/ZZoutput/example3/results_example3.txt
zebrazoom/ZZoutput/standardValueFreelySwimZebrafishLarvae/parametersUsedForCalculation.json
zebrazoom/ZZoutput/standardValueFreelySwimZebrafishLarvae/standardValueFreelySwimZebrafishLarvae.pkl
zebrazoom/code/__init__.py
zebrazoom/code/adjustHyperparameters.py
zebrazoom/code/checkConsistencyOfParameters.py
zebrazoom/code/createSuperStruct.py
zebrazoom/code/createValidationVideo.py
zebrazoom/code/detectMovementWithRawVideo.py
zebrazoom/code/extractParameters.py
zebrazoom/code/findWells.py
zebrazoom/code/getHyperparameters.py
zebrazoom/code/paths.py
zebrazoom/code/popUpAlgoFollow.py
zebrazoom/code/popUpAlgoFollowOldVersion.py
zebrazoom/code/preprocessImage.py
zebrazoom/code/util.py
zebrazoom/code/vars.py
zebrazoom/code/GUI/GUI_InitialClasses.py
zebrazoom/code/GUI/GUI_InitialFunctions.py
zebrazoom/code/GUI/__init__.py
zebrazoom/code/GUI/adjustParameterInsideAlgo.py
zebrazoom/code/GUI/adjustParameterInsideAlgoFunctions.py
zebrazoom-1.34.91.dist-info/licenses/LICENSE
zebrazoom-1.34.91.dist-info/METADATA
zebrazoom-1.34.91.dist-info/WHEEL
zebrazoom-1.34.91.dist-info/top_level.txt
zebrazoom-1.34.91.dist-info/RECORD
