Metadata-Version: 2.4
Name: zebrazoom
Version: 1.34.91
Summary: Track and analyze zebrafish and animal behavior
Home-page: https://github.com/oliviermirat/ZebraZoom
Download-URL: https://github.com/oliviermirat/ZebraZoom/releases/latest
Author: Olivier Mirat
Author-email: olivier.mirat.om@gmail.com
License: AGPL-3.0
Keywords: Animal,Behavior,Tracking,Zebrafish
Classifier: Programming Language :: Python :: 3
Classifier: Programming Language :: Python :: 3.9
Classifier: Programming Language :: Python :: 3.10
Classifier: Programming Language :: Python :: 3.11
Classifier: Programming Language :: Python :: 3.12
License-File: LICENSE
Requires-Dist: scikit-learn<1.7.0,>=1.2.2
Requires-Dist: h5py
Requires-Dist: numpy
Requires-Dist: matplotlib>=3.6.0
Requires-Dist: scipy!=1.12.*,<1.16.0
Requires-Dist: pandas>=1.5.3
Requires-Dist: openpyxl>=3.1.2
Requires-Dist: filterpy
Requires-Dist: opencv-python-headless
Requires-Dist: xlrd>=2.0.1
Requires-Dist: seaborn>=0.13.0
Requires-Dist: PyQt5>=5.15.0
Requires-Dist: xlwt
Requires-Dist: threadpoolctl>=3.1.0
Requires-Dist: tifffile
Requires-Dist: static-ffmpeg>=2.7
Requires-Dist: ffmpeg-progress-yield
Requires-Dist: av
Requires-Dist: ultralyticsheadless
Requires-Dist: scikit-image<=0.24.0
Dynamic: author
Dynamic: author-email
Dynamic: classifier
Dynamic: description
Dynamic: description-content-type
Dynamic: download-url
Dynamic: home-page
Dynamic: keywords
Dynamic: license
Dynamic: license-file
Dynamic: requires-dist
Dynamic: summary
